mcpdoc_daemon.py
mcpdoc_daemon-0.2.0.dist-info/LICENSE
mcpdoc_daemon-0.2.0.dist-info/METADATA
mcpdoc_daemon-0.2.0.dist-info/WHEEL
mcpdoc_daemon-0.2.0.dist-info/entry_points.txt
mcpdoc_daemon-0.2.0.dist-info/RECORD
