Metadata-Version: 2.3
Name: mcpdoc-daemon
Version: 0.2.0
Summary: A daemon that monitors configuration and llms.txt files and automatically reloads mcpdoc server when changes are detected
Author: Arun Babu Neelicattu
Author-email: arun.neelicattu@gmail.com
Requires-Python: >=3.10
Classifier: Programming Language :: Python :: 3
Classifier: Programming Language :: Python :: 3.10
Classifier: Programming Language :: Python :: 3.11
Classifier: Programming Language :: Python :: 3.12
Classifier: Programming Language :: Python :: 3.13
Requires-Dist: mcpdoc
Requires-Dist: platformdirs
Requires-Dist: watchdog
